helloworld/__init__.py
example_helloworld-1.0.dist-info/LICENSE
example_helloworld-1.0.dist-info/METADATA
example_helloworld-1.0.dist-info/WHEEL
example_helloworld-1.0.dist-info/top_level.txt
example_helloworld-1.0.dist-info/RECORD
